Workbook
Name pricing_strategy_Table: data!$A$1:$I$20

Sheet data
A1: Company | B1: value_index | C1: value_index | D1: Price | E1: Performance_Score | F1: value_rank | G1: price_rank | H1: pricing_gap | I1: pricing_strategy
A2: ACER | B2: 1.2854469e-05 | C2: =ROUND(B2,8)*100000 -> 1.285 | D2: 33461.813 | E2: 0.41941344 | F2: 2 | G2: 16 | H2: 14 | I2: Underpriced - Can Increase Price
A3: APPLE | B3: 6.6001255e-06 | C3: =ROUND(B3,8)*100000 -> 0.66 | D3: 88216.542 | E3: 0.55769608 | F3: 16 | G3: 5 | H3: -11 | I3: Premium - Brand Power Strategy
A4: ASUS | B4: 1.0005179e-05 | C4: =ROUND(B4,8)*100000 -> 1.001 | D4: 58022.093 | E4: 0.52622024 | F4: 6 | G4: 12 | H4: 6 | I4: Needs Repositioning
A5: CHUWI | B5: 7.5078148e-06 | C5: =ROUND(B5,8)*100000 -> 0.751 | D5: 16745.726 | E5: 0.11777778 | F5: 13 | G5: 17 | H5: 4 | I5: Needs Repositioning
A6: DELL | B6: 1.0254309e-05 | C6: =ROUND(B6,8)*100000 -> 1.025 | D6: 65963.045 | E6: 0.56656118 | F6: 5 | G6: 9 | H6: 4 | I6: Revenue Dominant — Portfolio Strength Strategy
A7: FUJITSU | B7: 1.4185012e-05 | C7: =ROUND(B7,8)*100000 -> 1.419 | D7: 38841.12 | E7: 0.54777778 | F7: 1 | G7: 15 | H7: 14 | I7: Underpriced - Can Increase Price
A8: GOOGLE | B8: 5.9167124e-06 | C8: =ROUND(B8,8)*100000 -> 0.592 | D8: 89386.08 | E8: 0.52027778 | F8: 18 | G8: 4 | H8: -14 | I8: Premium - Brand Power Strategy
A9: HP | B9: 1.0823484e-05 | C9: =ROUND(B9,8)*100000 -> 1.082 | D9: 54775.4 | E9: 0.50718384 | F9: 4 | G9: 14 | H9: 10 | I9: Underpriced - Can Increase Price
A10: HUAWEI | B10: 8.2501467e-06 | C10: =ROUND(B10,8)*100000 -> 0.825 | D10: 75870.72 | E10: 0.6275 | F10: 10 | G10: 8 | H10: -2 | I10: Needs Repositioning
A11: LENOVO | B11: 1.100615e-05 | C11: =ROUND(B11,8)*100000 -> 1.101 | D11: 57480.871 | E11: 0.52780888 | F11: 3 | G11: 13 | H11: 10 | I11: Underpriced - Can Increase Price
A12: LG | B12: 6.0943402e-06 | C12: =ROUND(B12,8)*100000 -> 0.609 | D12: 111834.72 | E12: 0.67444444 | F12: 17 | G12: 2 | H12: -15 | I12: Premium - Brand Power Strategy
A13: MEDIACOM | B13: 7.4075191e-06 | C13: =ROUND(B13,8)*100000 -> 0.741 | D13: 15717.6 | E13: 0.11321429 | F13: 14 | G13: 18 | H13: 4 | I13: Needs Repositioning
... A20: XIAOMI | B20: 9.3789424e-06 | C20: =ROUND(B20,8)*100000 -> 0.938 | D20: 60390.882 | E20: 0.55333333 | F20: 8 | G20: 11 | H20: 3 | I20: Needs Repositioning

Sheet KPI Summary
B3: Brand | C3: Avg Price | D3: High Value % | E3: Value Efficiency Index (Scaled) | F3: Estimated Revenue | G3: Strategy Recommendation
B4: ACER | C4: =_xlfn.XLOOKUP(B4,data!$A$2:$A$20,data!$D$2:$D$20) -> 33461.813 | D4: =_xlfn.XLOOKUP(B4,[1]Strategic_Summary!$B$6:$B$24,[1]Strategic_Summary!$C$6:$C$24) -> 0.63095238 | E4: =_xlfn.XLOOKUP(B4,data!$A$2:$A$20,data!$C$2:$C$20) -> 1.285 | F4: =_xlfn.XLOOKUP(B4,[1]Sheet1!$A$2:$A$20,[1]Sheet1!$B$2:$B$20) -> 35387824 | G4: =_xlfn.XLOOKUP(B4,data!$A$2:$A$20,data!$I$2:$I$20) -> Underpriced - Can Increase Price
B5: APPLE | C5: =_xlfn.XLOOKUP(B5,data!$A$2:$A$20,data!$D$2:$D$20) -> 88216.542 | D5: =_xlfn.XLOOKUP(B5,[1]Strategic_Summary!$B$6:$B$24,[1]Strategic_Summary!$C$6:$C$24) -> 0 | E5: =_xlfn.XLOOKUP(B5,data!$A$2:$A$20,data!$C$2:$C$20) -> 0.66 | F5: =_xlfn.XLOOKUP(B5,[1]Sheet1!$A$2:$A$20,[1]Sheet1!$B$2:$B$20) -> 9405530.1 | G5: =_xlfn.XLOOKUP(B5,data!$A$2:$A$20,data!$I$2:$I$20) -> Premium - Brand Power Strategy
B6: ASUS | C6: =_xlfn.XLOOKUP(B6,data!$A$2:$A$20,data!$D$2:$D$20) -> 58022.093 | D6: =_xlfn.XLOOKUP(B6,[1]Strategic_Summary!$B$6:$B$24,[1]Strategic_Summary!$C$6:$C$24) -> 0.26984127 | E6: =_xlfn.XLOOKUP(B6,data!$A$2:$A$20,data!$C$2:$C$20) -> 1.001 | F6: =_xlfn.XLOOKUP(B6,[1]Sheet1!$A$2:$A$20,[1]Sheet1!$B$2:$B$20) -> 66119836 | G6: =_xlfn.XLOOKUP(B6,data!$A$2:$A$20,data!$I$2:$I$20) -> Needs Repositioning
B7: CHUWI | C7: =_xlfn.XLOOKUP(B7,data!$A$2:$A$20,data!$D$2:$D$20) -> 16745.726 | D7: =_xlfn.XLOOKUP(B7,[1]Strategic_Summary!$B$6:$B$24,[1]Strategic_Summary!$C$6:$C$24) -> 0 | E7: =_xlfn.XLOOKUP(B7,data!$A$2:$A$20,data!$C$2:$C$20) -> 0.751 | F7: =_xlfn.XLOOKUP(B7,[1]Sheet1!$A$2:$A$20,[1]Sheet1!$B$2:$B$20) -> 356443.73 | G7: =_xlfn.XLOOKUP(B7,data!$A$2:$A$20,data!$I$2:$I$20) -> Needs Repositioning
B8: DELL | C8: =_xlfn.XLOOKUP(B8,data!$A$2:$A$20,data!$D$2:$D$20) -> 65963.045 | D8: =_xlfn.XLOOKUP(B8,[1]Strategic_Summary!$B$6:$B$24,[1]Strategic_Summary!$C$6:$C$24) -> 0.34177215 | E8: =_xlfn.XLOOKUP(B8,data!$A$2:$A$20,data!$C$2:$C$20) -> 1.025 | F8: =_xlfn.XLOOKUP(B8,[1]Sheet1!$A$2:$A$20,[1]Sheet1!$B$2:$B$20) -> 1.3428918e+08 | G8: Revenue Dominant — Portfolio Strength Strategy
B9: FUJITSU | C9: =_xlfn.XLOOKUP(B9,data!$A$2:$A$20,data!$D$2:$D$20) -> 38841.12 | D9: =_xlfn.XLOOKUP(B9,[1]Strategic_Summary!$B$6:$B$24,[1]Strategic_Summary!$C$6:$C$24) -> 1 | E9: =_xlfn.XLOOKUP(B9,data!$A$2:$A$20,data!$C$2:$C$20) -> 1.419 | F9: =_xlfn.XLOOKUP(B9,[1]Sheet1!$A$2:$A$20,[1]Sheet1!$B$2:$B$20) -> 1657913.8 | G9: =_xlfn.XLOOKUP(B9,data!$A$2:$A$20,data!$I$2:$I$20) -> Underpriced - Can Increase Price
B10: GOOGLE | C10: =_xlfn.XLOOKUP(B10,data!$A$2:$A$20,data!$D$2:$D$20) -> 89386.08 | D10: =_xlfn.XLOOKUP(B10,[1]Strategic_Summary!$B$6:$B$24,[1]Strategic_Summary!$C$6:$C$24) -> 0 | E10: =_xlfn.XLOOKUP(B10,data!$A$2:$A$20,data!$C$2:$C$20) -> 0.592 | F10: =_xlfn.XLOOKUP(B10,[1]Sheet1!$A$2:$A$20,[1]Sheet1!$B$2:$B$20) -> 1559718.7 | G10: =_xlfn.XLOOKUP(B10,data!$A$2:$A$20,data!$I$2:$I$20) -> Premium - Brand Power Strategy
B11: HP | C11: =_xlfn.XLOOKUP(B11,data!$A$2:$A$20,data!$D$2:$D$20) -> 54775.4 | D11: =_xlfn.XLOOKUP(B11,[1]Strategic_Summary!$B$6:$B$24,[1]Strategic_Summary!$C$6:$C$24) -> 0.31891892 | E11: =_xlfn.XLOOKUP(B11,data!$A$2:$A$20,data!$C$2:$C$20) -> 1.082 | F11: =_xlfn.XLOOKUP(B11,[1]Sheet1!$A$2:$A$20,[1]Sheet1!$B$2:$B$20) -> 93536773 | G11: =_xlfn.XLOOKUP(B11,data!$A$2:$A$20,data!$I$2:$I$20) -> Underpriced - Can Increase Price
B12: HUAWEI | C12: =_xlfn.XLOOKUP(B12,data!$A$2:$A$20,data!$D$2:$D$20) -> 75870.72 | D12: =_xlfn.XLOOKUP(B12,[1]Strategic_Summary!$B$6:$B$24,[1]Strategic_Summary!$C$6:$C$24) -> 0 | E12: =_xlfn.XLOOKUP(B12,data!$A$2:$A$20,data!$C$2:$C$20) -> 0.825 | F12: =_xlfn.XLOOKUP(B12,[1]Sheet1!$A$2:$A$20,[1]Sheet1!$B$2:$B$20) -> 1293798.2 | G12: =_xlfn.XLOOKUP(B12,data!$A$2:$A$20,data!$I$2:$I$20) -> Needs Repositioning
B13: LENOVO | C13: =_xlfn.XLOOKUP(B13,data!$A$2:$A$20,data!$D$2:$D$20) -> 57480.871 | D13: =_xlfn.XLOOKUP(B13,[1]Strategic_Summary!$B$6:$B$24,[1]Strategic_Summary!$C$6:$C$24) -> 0.40869565 | E13: =_xlfn.XLOOKUP(B13,data!$A$2:$A$20,data!$C$2:$C$20) -> 1.101 | F13: =_xlfn.XLOOKUP(B13,[1]Sheet1!$A$2:$A$20,[1]Sheet1!$B$2:$B$20) -> 1.22219e+08 | G13: =_xlfn.XLOOKUP(B13,data!$A$2:$A$20,data!$I$2:$I$20) -> Underpriced - Can Increase Price
B14: LG | C14: =_xlfn.XLOOKUP(B14,data!$A$2:$A$20,data!$D$2:$D$20) -> 111834.72 | D14: =_xlfn.XLOOKUP(B14,[1]Strategic_Summary!$B$6:$B$24,[1]Strategic_Summary!$C$6:$C$24) -> 0 | E14: =_xlfn.XLOOKUP(B14,data!$A$2:$A$20,data!$C$2:$C$20) -> 0.609 | F14: =_xlfn.XLOOKUP(B14,[1]Sheet1!$A$2:$A$20,[1]Sheet1!$B$2:$B$20) -> 2103547.7 | G14: =_xlfn.XLOOKUP(B14,data!$A$2:$A$20,data!$I$2:$I$20) -> Premium - Brand Power Strategy
B15: MEDIACOM | C15: =_xlfn.XLOOKUP(B15,data!$A$2:$A$20,data!$D$2:$D$20) -> 15717.6 | D15: =_xlfn.XLOOKUP(B15,[1]Strategic_Summary!$B$6:$B$24,[1]Strategic_Summary!$C$6:$C$24) -> 0 | E15: =_xlfn.XLOOKUP(B15,data!$A$2:$A$20,data!$C$2:$C$20) -> 0.741 | F15: =_xlfn.XLOOKUP(B15,[1]Sheet1!$A$2:$A$20,[1]Sheet1!$B$2:$B$20) -> 796749.12 | G15: =_xlfn.XLOOKUP(B15,data!$A$2:$A$20,data!$I$2:$I$20) -> Needs Repositioning
B16: MICROSOFT | C16: =_xlfn.XLOOKUP(B16,data!$A$2:$A$20,data!$D$2:$D$20) -> 85903.788 | D16: =_xlfn.XLOOKUP(B16,[1]Strategic_Summary!$B$6:$B$24,[1]Strategic_Summary!$C$6:$C$24) -> 0 | E16: =_xlfn.XLOOKUP(B16,data!$A$2:$A$20,data!$C$2:$C$20) -> 0.734 | F16: =_xlfn.XLOOKUP(B16,[1]Sheet1!$A$2:$A$20,[1]Sheet1!$B$2:$B$20) -> 3572208.2 | G16: =_xlfn.XLOOKUP(B16,data!$A$2:$A$20,data!$I$2:$I$20) -> Needs Repositioning
B17: MSI | C17: =_xlfn.XLOOKUP(B17,data!$A$2:$A$20,data!$D$2:$D$20) -> 95357.786 | D17: =_xlfn.XLOOKUP(B17,[1]Strategic_Summary!$B$6:$B$24,[1]Strategic_Summary!$C$6:$C$24) -> 0 | E17: =_xlfn.XLOOKUP(B17,data!$A$2:$A$20,data!$C$2:$C$20) -> 0.774 | F17: =_xlfn.XLOOKUP(B17,[1]Sheet1!$A$2:$A$20,[1]Sheet1!$B$2:$B$20) -> 23137373 | G17: =_xlfn.XLOOKUP(B17,data!$A$2:$A$20,data!$I$2:$I$20) -> Premium - Brand Power Strategy
B18: RAZER | C18: =_xlfn.XLOOKUP(B18,data!$A$2:$A$20,data!$D$2:$D$20) -> 201345.12 | D18: =_xlfn.XLOOKUP(B18,[1]Strategic_Summary!$B$6:$B$24,[1]Strategic_Summary!$C$6:$C$24) -> 0 | E18: =_xlfn.XLOOKUP(B18,data!$A$2:$A$20,data!$C$2:$C$20) -> 0.469 | F18: =_xlfn.XLOOKUP(B18,[1]Sheet1!$A$2:$A$20,[1]Sheet1!$B$2:$B$20) -> 4085297.3 | G18: =_xlfn.XLOOKUP(B18,data!$A$2:$A$20,data!$I$2:$I$20) -> Premium - Brand Power Strategy
B19: SAMSUNG | C19: =_xlfn.XLOOKUP(B19,data!$A$2:$A$20,data!$D$2:$D$20) -> 80332.92 | D19: =_xlfn.XLOOKUP(B19,[1]Strategic_Summary!$B$6:$B$24,[1]Strategic_Summary!$C$6:$C$24) -> 0 | E19: =_xlfn.XLOOKUP(B19,data!$A$2:$A$20,data!$C$2:$C$20) -> 0.761 | F19: =_xlfn.XLOOKUP(B19,[1]Sheet1!$A$2:$A$20,[1]Sheet1!$B$2:$B$20) -> 4776552 | G19: =_xlfn.XLOOKUP(B19,data!$A$2:$A$20,data!$I$2:$I$20) -> Needs Repositioning
B20: TOSHIBA | C20: =_xlfn.XLOOKUP(B20,data!$A$2:$A$20,data!$D$2:$D$20) -> 64967.813 | D20: =_xlfn.XLOOKUP(B20,[1]Strategic_Summary!$B$6:$B$24,[1]Strategic_Summary!$C$6:$C$24) -> 0.24390244 | E20: =_xlfn.XLOOKUP(B20,data!$A$2:$A$20,data!$C$2:$C$20) -> 0.982 | F20: =_xlfn.XLOOKUP(B20,[1]Sheet1!$A$2:$A$20,[1]Sheet1!$B$2:$B$20) -> 23699157 | G20: =_xlfn.XLOOKUP(B20,data!$A$2:$A$20,data!$I$2:$I$20) -> Needs Repositioning
... B22: XIAOMI | C22: =_xlfn.XLOOKUP(B22,data!$A$2:$A$20,data!$D$2:$D$20) -> 60390.882 | D22: =_xlfn.XLOOKUP(B22,[1]Strategic_Summary!$B$6:$B$24,[1]Strategic_Summary!$C$6:$C$24) -> 0 | E22: =_xlfn.XLOOKUP(B22,data!$A$2:$A$20,data!$C$2:$C$20) -> 0.938 | F22: =_xlfn.XLOOKUP(B22,[1]Sheet1!$A$2:$A$20,[1]Sheet1!$B$2:$B$20) -> 2177899.9 | G22: =_xlfn.XLOOKUP(B22,data!$A$2:$A$20,data!$I$2:$I$20) -> Needs Repositioning
B23: Average | C23: =AVERAGE(C4:C22) -> 68786.616 | F23: =AVERAGE(F4:F22) -> 27915459
C26: X(Price) | F26: Y(Revenue) | H26: X (Price) | I26: Y (Revenue)
C27: ='KPI Summary'!C23 -> 68786.616 | F27: 0 | H27: 0 | I27: ='KPI Summary'!$F$23 -> 27915459
C28: ='KPI Summary'!C23 -> 68786.616 | F28: =MAX('KPI Summary'!F4:F22) -> 1.3428918e+08 | H28: =MAX('KPI Summary'!C4:C22) -> 201345.12 | I28: ='KPI Summary'!$F$23 -> 27915459

Sheet Strategic Quadrant Chart

Sheet Executive_Conclusion
C3: Final Pricing Strategy Conclusion
C5: 1. Dell
C6: Dell dominates total revenue primarily through portfolio breadth and brand strength rather than leading in pure value efficiency.
C7: Its balanced positioning enables sustained revenue leadership without relying on aggressive price reductions.
C9: 2. Lenovo
C10: Lenovo combines strong value efficiency with high revenue performance, positioning it as a balanced competitive leader.
C11: The brand demonstrates effective alignment between pricing and performance, indicating strategic stability.
C13: 3. Fujitsu
C14: Fujitsu exhibits the highest value efficiency index yet captures comparatively low revenue.
C15: This suggests an under-monetized opportunity, where selective price increases or enhanced marketing investment could unlock
C16: higher revenue potential without compromising competitiveness.
C18: 4. Acer & HP
... C36: Selective optimization — not industry-wide discounting — is the recommended approach.
